AlgebraicGraphAlgorithmsLectureNotesStanfordCs367/README.md
AlgebraicGraphAlgorithmsLectureNotesStanfordCs367/__init__.py
AlgebraicGraphAlgorithmsLectureNotesStanfordCs367/__main__.py
AlgebraicGraphAlgorithmsLectureNotesStanfordCs367/file.pdf
AlgebraicGraphAlgorithmsLectureNotesStanfordCs367/index.html
algebraic_graph_algorithms_lecture_notes_stanford_cs367-2024.3.1.0.dist-info/METADATA
algebraic_graph_algorithms_lecture_notes_stanford_cs367-2024.3.1.0.dist-info/WHEEL
algebraic_graph_algorithms_lecture_notes_stanford_cs367-2024.3.1.0.dist-info/entry_points.txt
algebraic_graph_algorithms_lecture_notes_stanford_cs367-2024.3.1.0.dist-info/top_level.txt
algebraic_graph_algorithms_lecture_notes_stanford_cs367-2024.3.1.0.dist-info/RECORD
